redis_namespace/__init__.py
redis_namespace/_version.py
redis_namespace-3.0.1.1.dist-info/LICENSE
redis_namespace-3.0.1.1.dist-info/METADATA
redis_namespace-3.0.1.1.dist-info/WHEEL
redis_namespace-3.0.1.1.dist-info/top_level.txt
redis_namespace-3.0.1.1.dist-info/RECORD
