Metadata-Version: 2.1
Name: redis-namespace
Version: 3.0.1.1
Summary: namespaced subset of your redis keyspace
Home-page: https://github.com/guokr/redis-namespace
Author: zrq495
Author-email: zrq495@gmail.com
License: MIT
Keywords: redis namespace,redis prefix
Platform: UNKNOWN
Classifier: Programming Language :: Python :: 2
Classifier: License :: OSI Approved :: MIT License
Classifier: Operating System :: OS Independent
